First_package/__init__.py
First_package/mongo_crud.py
components/__init__.py
components/data_ingestion.py
components/data_trainer.py
components/data_transformation.py
components/model_evaluation.py
pipline/__init__.py
pipline/prediction_pipline.py
pipline/training_pipline.py
utils/__init__.py
utils/utils.py
alipourranjbar111-0.1.0.dist-info/LICENSE
alipourranjbar111-0.1.0.dist-info/METADATA
alipourranjbar111-0.1.0.dist-info/WHEEL
alipourranjbar111-0.1.0.dist-info/top_level.txt
alipourranjbar111-0.1.0.dist-info/RECORD
